.bzrignore
AUTHORS
ChangeLog
HACKING.md
LICENSE
MANIFEST.in
Makefile
README.rst
pip.sh
requirements.txt
setup.cfg
setup.py
tarmac_tests.sh
test-requirements.txt
tox.ini
.github/workflows/build.yml
bin/README
bin/chlp
bin/contrib/charmsupport/charmsupport
bin/contrib/saltstack/salt-call
charmhelpers/__init__.py
charmhelpers/context.py
charmhelpers/coordinator.py
charmhelpers/osplatform.py
charmhelpers.egg-info/PKG-INFO
charmhelpers.egg-info/SOURCES.txt
charmhelpers.egg-info/dependency_links.txt
charmhelpers.egg-info/not-zip-safe
charmhelpers.egg-info/pbr.json
charmhelpers.egg-info/requires.txt
charmhelpers.egg-info/top_level.txt
charmhelpers/cli/README.rst
charmhelpers/cli/__init__.py
charmhelpers/cli/benchmark.py
charmhelpers/cli/commands.py
charmhelpers/cli/hookenv.py
charmhelpers/cli/host.py
charmhelpers/cli/unitdata.py
charmhelpers/contrib/__init__.py
charmhelpers/contrib/python.py
charmhelpers/contrib/ansible/__init__.py
charmhelpers/contrib/benchmark/__init__.py
charmhelpers/contrib/charmhelpers/IMPORT
charmhelpers/contrib/charmhelpers/__init__.py
charmhelpers/contrib/charmsupport/IMPORT
charmhelpers/contrib/charmsupport/__init__.py
charmhelpers/contrib/charmsupport/nrpe.py
charmhelpers/contrib/charmsupport/volumes.py
charmhelpers/contrib/database/__init__.py
charmhelpers/contrib/database/mysql.py
charmhelpers/contrib/hahelpers/__init__.py
charmhelpers/contrib/hahelpers/apache.py
charmhelpers/contrib/hahelpers/cluster.py
charmhelpers/contrib/hardening/README.hardening.md
charmhelpers/contrib/hardening/__init__.py
charmhelpers/contrib/hardening/harden.py
charmhelpers/contrib/hardening/templating.py
charmhelpers/contrib/hardening/utils.py
charmhelpers/contrib/hardening/apache/__init__.py
charmhelpers/contrib/hardening/apache/checks/__init__.py
charmhelpers/contrib/hardening/apache/checks/config.py
charmhelpers/contrib/hardening/apache/templates/99-hardening.conf
charmhelpers/contrib/hardening/apache/templates/alias.conf
charmhelpers/contrib/hardening/audits/__init__.py
charmhelpers/contrib/hardening/audits/apache.py
charmhelpers/contrib/hardening/audits/apt.py
charmhelpers/contrib/hardening/audits/file.py
charmhelpers/contrib/hardening/defaults/apache.yaml
